{
  "version": "5",
  "dialect": "pg",
  "entries": [
    {
      "idx": 0,
      "version": "5",
      "when": 1706310092285,
      "tag": "0000_mighty_proudstar",
      "breakpoints": true
    },
    {
      "idx": 1,
      "version": "5",
      "when": 1708351520126,
      "tag": "0001_organic_stark_industries",
      "breakpoints": true
    },
    {
      "idx": 2,
      "version": "7",
      "when": 1718917479814,
      "tag": "0002_awesome_kitty_pryde",
      "breakpoints": true
    },
    {
      "idx": 3,
      "version": "7",
      "when": 1719240348339,
      "tag": "0003_charming_morlun",
      "breakpoints": true
    },
    {
      "idx": 4,
      "version": "7",
      "when": 1726606243061,
      "tag": "0004_bitter_spyke",
      "breakpoints": true
    },
    {
      "idx": 5,
      "version": "7",
      "when": 1728340423596,
      "tag": "0005_grey_shaman",
      "breakpoints": true
    },
    {
      "idx": 6,
      "version": "7",
      "when": 1728582519150,
      "tag": "0006_loose_eternals",
      "breakpoints": true
    },
    {
      "idx": 7,
      "version": "7",
      "when": 1728608204930,
      "tag": "0007_supreme_doctor_doom",
      "breakpoints": true
    },
    {
      "idx": 8,
      "version": "7",
      "when": 1728609405676,
      "tag": "0008_watery_blur",
      "breakpoints": true
    },
    {
      "idx": 9,
      "version": "7",
      "when": 1739730145711,
      "tag": "0009_magical_dragon_lord",
      "breakpoints": true
    },
    {
      "idx": 10,
      "version": "7",
      "when": 1741807473222,
      "tag": "0010_left_warstar",
      "breakpoints": true
    },
    {
      "idx": 11,
      "version": "7",
      "when": 1749161728043,
      "tag": "0011_fat_richard_fisk",
      "breakpoints": true
    },
    {
      "idx": 12,
      "version": "7",
      "when": 1749162369080,
      "tag": "0012_black_harry_osborn",
      "breakpoints": true
    },
    {
      "idx": 13,
      "version": "7",
      "when": 1759345496412,
      "tag": "0013_wandering_frog_thor",
      "breakpoints": true
    }
  ]
}